{
  "entrypoints": [
    "main"
  ],
  "origins": {
    "190": [
      190
    ],
    "17896441": [
      869,
      401
    ],
    "main": [
      354,
      869,
      792
    ],
    "runtime~main": [
      792,
      869,
      354
    ],
    "0058b4c6": [
      849
    ],
    "0e384e19": [
      976
    ],
    "5281b7a2": [
      443
    ],
    "5e95c892": [
      647
    ],
    "6476eba6": [
      722
    ],
    "a7bd4aaa": [
      98
    ],
    "a94703ab": [
      869,
      48
    ],
    "aba21aa0": [
      742
    ],
    "styles": [
      48,
      354,
      401,
      792,
      869
    ]
  },
  "assets": {
    "48": {
      "js": [
        {
          "file": "assets/js/a94703ab.5967f1ee.js",
          "hash": "a88f8575ca8fc47d",
          "publicPath": "/assets/js/a94703ab.5967f1ee.js"
        }
      ]
    },
    "98": {
      "js": [
        {
          "file": "assets/js/a7bd4aaa.3d00a04d.js",
          "hash": "24169e2ead28c6d5",
          "publicPath": "/assets/js/a7bd4aaa.3d00a04d.js"
        }
      ]
    },
    "190": {
      "js": [
        {
          "file": "assets/js/190.6450eb39.js",
          "hash": "670f6cf11fe07e65",
          "publicPath": "/assets/js/190.6450eb39.js"
        }
      ]
    },
    "354": {
      "js": [
        {
          "file": "assets/js/runtime~main.4aef7aa3.js",
          "hash": "c4f8eed8fd2f78bf",
          "publicPath": "/assets/js/runtime~main.4aef7aa3.js"
        }
      ]
    },
    "401": {
      "js": [
        {
          "file": "assets/js/17896441.c5bfb6dd.js",
          "hash": "208dc20af9e5ded2",
          "publicPath": "/assets/js/17896441.c5bfb6dd.js"
        }
      ]
    },
    "443": {
      "js": [
        {
          "file": "assets/js/5281b7a2.c654bca0.js",
          "hash": "1f3970fe2e729b64",
          "publicPath": "/assets/js/5281b7a2.c654bca0.js"
        }
      ]
    },
    "647": {
      "js": [
        {
          "file": "assets/js/5e95c892.a0d6f619.js",
          "hash": "ab78018b0217e38e",
          "publicPath": "/assets/js/5e95c892.a0d6f619.js"
        }
      ]
    },
    "722": {
      "js": [
        {
          "file": "assets/js/6476eba6.feeb5516.js",
          "hash": "568b545a36e5249e",
          "publicPath": "/assets/js/6476eba6.feeb5516.js"
        }
      ]
    },
    "742": {
      "js": [
        {
          "file": "assets/js/aba21aa0.6df63659.js",
          "hash": "392f8065ec6835d5",
          "publicPath": "/assets/js/aba21aa0.6df63659.js"
        }
      ]
    },
    "792": {
      "js": [
        {
          "file": "assets/js/main.1db08b38.js",
          "hash": "dd1eb5a5e148513f",
          "publicPath": "/assets/js/main.1db08b38.js"
        }
      ]
    },
    "849": {
      "js": [
        {
          "file": "assets/js/0058b4c6.ef62a5d2.js",
          "hash": "d5ddd196ef5d053e",
          "publicPath": "/assets/js/0058b4c6.ef62a5d2.js"
        }
      ]
    },
    "869": {
      "css": [
        {
          "file": "assets/css/styles.5052fab2.css",
          "hash": "0c8188a017ea59d2",
          "publicPath": "/assets/css/styles.5052fab2.css"
        }
      ]
    },
    "976": {
      "js": [
        {
          "file": "assets/js/0e384e19.1af4e199.js",
          "hash": "3a8bc3622e7057cb",
          "publicPath": "/assets/js/0e384e19.1af4e199.js"
        }
      ]
    }
  }
}